README.rst
setup.py
BeanDateUtils.egg-info/PKG-INFO
BeanDateUtils.egg-info/SOURCES.txt
BeanDateUtils.egg-info/dependency_links.txt
BeanDateUtils.egg-info/top_level.txt
BeanDateUtils.egg-info/zip-safe
date_utils/__init__.py
date_utils/date_utils.py