Metadata-Version: 1.1
Name: BeanDateUtils
Version: 0.3
Summary: A Python library for date compute.
Home-page: https://github.com/beansKingdom/DateUtils
Author: Hly
Author-email: hlyaction@gmail.com
License: MIT
Platform: UNKNOWN
Classifier: Programming Language :: Python :: 3
Classifier: License :: OSI Approved :: MIT License
Classifier: Operating System :: OS Independent
